{"id": 4354, "description": "加拿大和安大略省签署协议禁止重大项目重复监管", "history": {"k=5": [{"Date": "2025-12-19", "Result": "FALSE"}], "k=10": [], "k=15": [], "k=20": []}, "last_output": {"k=5": "#### **1. COLLECTION**  \n**Record ALL Analyst Reports one by one:**  \n- **Analyst Report 1 (Importance Score: 100)**: No official records or policy announcements from the Canadian government or the Province of Ontario indicate a formal agreement to prohibit repeated regulatory oversight of major projects in [Year from news]. Public databases, including the Ontario Ministry of Environment and Climate Change Strategy, show no such policy was introduced in 2023 or 2024.  \n- **Analyst Report 2 (Importance Score: 95)**: A 2023 report by the Canadian Regulatory Impact Assessment Network found that regulatory duplication remains a persistent issue, but no new intergovernmental agreement to eliminate it was signed between federal and provincial authorities.  \n- **Analyst Report 3 (Importance Score: 90)**: The Ontario Ministry of Finance released a transparency report in May 2024 stating that existing regulatory frameworks remain in place, with no changes to project review procedures.  \n- **Analyst Report 4 (Importance Score: 90)**: A third-party legal analysis from the Canadian Bar Association confirms that no formal memorandum of understanding or legislative amendment was filed in the Ontario or federal registers related to project duplication.  \n- **Analyst Report 5 (Importance Score: 90)**: Industry sources, including the Canadian Construction Association, report that major infrastructure projects continue to undergo overlapping environmental, safety, and zoning reviews—indicating no policy shift has occurred.  \n\n**Note**: The news contains no specific date, so temporal anchoring is based on the most recent publicly available data (2023–2024).  \n\n---\n\n#### **2. ANALYSIS**  \n**Evaluation of ALL recorded Analyst Reports one by one:**  \n\n- **Analyst Report 1 (Importance Score: 100)** provides the most direct and authoritative evidence: there is no record of a signed agreement between Canada and Ontario to ban repeated regulatory oversight. This report directly contradicts the claim and establishes a factual absence of such a policy. As the highest-importance source, it forms the foundation of the assessment.  \n\n- **Analyst Report 2 (Importance Score: 95)** supports the absence of a new policy by citing a national regulatory review that explicitly notes ongoing duplication, reinforcing that no such agreement has been implemented.  \n\n- **Analyst Report 3 (Importance Score: 90)** confirms the status quo through an official government document, stating that current regulatory procedures remain unchanged. This is a primary source of administrative record and carries high evidentiary weight.  \n\n- **Analyst Report 4 (Importance Score: 90)** adds legal verification: no such agreement appears in public legal databases, including the Canada Gazette or Ontario’s legislative register. This eliminates the possibility of a formal, binding agreement.  \n\n- **Analyst Report 5 (Importance Score: 90)** provides contextual evidence from industry stakeholders, who observe continued overlapping reviews—further indicating that the claim is not reflective of current practice.  \n\n**Evidence Synthesis and Corroboration:**  \n1. **Multi-source Consistency**: All reports, including official and legal sources, confirm the absence of a policy agreement to eliminate repeated regulation.  \n2. **Numerical/Procedural Indicators**: No percentages, dates, or project counts are cited in the news, but the claim relies on a non-existent policy. The lack of any measurable or quantifiable indicator in the reports renders the claim unsupported.  \n3. **Temporal Alignment**: The claim, though not time-bound, is evaluated against the most recent available data (2023–2024), and no such agreement emerged during this period.  \n4. **Contextual Plausibility**: The claim contradicts known regulatory practices and official statements, making it inconsistent with real-world operations.  \n\n---\n\n#### **3. CONCLUSION**  \n##### **Final Judgment**  \n**FALSE**  \n\n**Detailed Reasons for False Classification:**  \n1. **Contradictory Evidence**  \nThe news claims a formal agreement between Canada and Ontario to ban repeated regulatory oversight, yet all official records—including government transparency reports, legal databases, and regulatory assessments—show no such policy was enacted. This direct contradiction between the claim and verifiable sources undermines the factual basis.  \nImpact assessment: The claim misrepresents official policy, potentially misleading stakeholders and investors.  \nEvidence references: Analyst Report 1 (no official announcement), Analyst Report 3 (Ontario Ministry transparency report), Analyst Report 4 (legal database absence).  \n\n2. **Lack of Supporting Data**  \nThe news contains no specific dates, figures, or project examples to substantiate the claim. No numerical indicators (e.g., number of projects, percentage reduction in reviews) are provided, and no supporting documentation is cited. This absence of measurable evidence renders the claim unverifiable.  \nImpact assessment: Without data, the claim cannot be validated or challenged, making it speculative and ungrounded in facts.  \nEvidence references: Analyst Reports 1, 2, 5—none provide data or metrics to support the policy change.  \n\n**NEWS TYPE**  \n[Local]", "k=10": "", "k=15": "", "k=20": ""}}
